LICENSE
MANIFEST.in
README.md
setup.py
barplots/__init__.py
barplots/__version__.py
barplots/barplot.py
barplots/barplots.py
barplots.egg-info/PKG-INFO
barplots.egg-info/SOURCES.txt
barplots.egg-info/dependency_links.txt
barplots.egg-info/requires.txt
barplots.egg-info/top_level.txt
barplots/utils/__init__.py
barplots/utils/bar_positions.py
barplots/utils/get_axes.py
barplots/utils/get_best_match.py
barplots/utils/get_jumps.py
barplots/utils/get_levels.py
barplots/utils/get_max_bar_length.py
barplots/utils/get_max_bar_position.py
barplots/utils/plot_bar.py
barplots/utils/plot_bar_labels.py
barplots/utils/plot_bars.py
barplots/utils/plot_boxplot.py
barplots/utils/plot_boxplots.py
barplots/utils/remove_duplicated_legend_labels.py
barplots/utils/save_picture.py
barplots/utils/text_positions.py
tests/test_bar_positions.py
tests/test_barplots.py
tests/test_simple_barplots.py
tests/test_single.py
tests/test_version.py
tests/test_wrong_parameters.py