Metadata-Version: 2.1
Name: barplots
Version: 1.2.1
Summary: Python package to easily make barplots from multi-indexed dataframes.
Home-page: https://github.com/LucaCappelletti94/barplots
Author: Luca Cappelletti
Author-email: cappelletti.luca94@gmail.com
License: MIT
Platform: UNKNOWN
Classifier: Development Status :: 3 - Alpha
Classifier: License :: OSI Approved :: MIT License
Classifier: Programming Language :: Python :: 3
Provides-Extra: test
License-File: LICENSE
